LICENSE
MANIFEST.in
README.rst
setup.py
text_histogram.py
text_histogram32.egg-info/PKG-INFO
text_histogram32.egg-info/SOURCES.txt
text_histogram32.egg-info/dependency_links.txt
text_histogram32.egg-info/top_level.txt
text_histogram32.egg-info/zip-safe