Metadata-Version: 2.1
Name: text-histogram32
Version: 0.0.7
Summary: A dependency-free library to quickly make ascii/text histograms from data.
Home-page: https://github.com/clach04/text_histogram32
Author: Andy Kish, Jehiah Czebotar, Jay Deiman, Jon Lundy, Chris Clark
License: Apache License, Version 2.0
Platform: any
Classifier: License :: OSI Approved :: Apache Software License
Classifier: Programming Language :: Python :: 3
Classifier: Programming Language :: Python :: 2
Classifier: Development Status :: 4 - Beta
Classifier: Environment :: Console
Classifier: Intended Audience :: Developers
Classifier: Topic :: Terminals
Classifier: Topic :: Scientific/Engineering :: Mathematics
License-File: LICENSE
